[
  {
    "day": "1",
    "events": [
      {
        "desc": [
          "img src=\"http://www.jazz.co.jp/LiveHouse/Schedule/images/28464.jpg\" border=\"0\"",
          "Aokki(sax)",
          "滝野聡(gt)",
          "阿部義徳(p)",
          "箭島裕治(b)",
          "ジーン重村(ds)",
          "多方面で活躍中のSax Player、Aokkiのリーダーバンド。",
          "オリジナルを中心とした彼独特の世界観と、強力なメンバーと共に創り上げるGrooveをお楽しみ頂けます。",
          "予約：2,500円",
          "当日：3,000円",
          "別途2ドリンク1,200円"
        ],
        "begin": "2010-09-01T20:00:00+09:00",
        "end": "2010-09-01T23:00:00+09:00",
        "title": "Aokkiバンド"
      }
    ]
  },
  {
    "day": "2",
    "events": [
      {
        "desc": [
          "img src=\"http://somethinjazz.com/img/spice.jpg\" border=\"0\"",
          "かわ島崇文(sax)",
          "佐藤ひろのすけ(p)",
          "村上弘樹(ds)",
          "岩崎恵一(b)",
          "パフェと言っても、甘いだけじゃない、刺激的な何か入ってます。",
          "予約:2,500円",
          "当日:3,000円",
          "別途1ドリンク600円"
        ],
        "begin": "2010-09-02T20:00:00+09:00",
        "end": "2010-09-02T23:00:00+09:00",
        "title": "SPICE PARFAIT"
      }
    ]
  },
  {
    "day": "3",
    "events": [
      {
        "desc": [
          "img src=\"http://somethinjazz.com/img/wally.jpg\" border=\"0\"",
          "石戸谷斉(tb)",
          "上條頌(g)",
          "伊原アニキひろし(g)",
          "滝元ケンシ(b)",
          "大井勇(ds)",
          "チャージ：2,500円",
          "(フリードリンク付)"
        ],
        "begin": "2010-09-03T20:00:00+09:00",
        "end": "2010-09-03T23:00:00+09:00",
        "title": "wally's funk night"
      }
    ]
  },
  {
    "day": "4",
    "events": [
      {
        "desc": [],
        "begin": "2010-09-04T12:00:00+09:00",
        "end": "2010-09-04T18:00:00+09:00",
        "title": "貸切 - 第5回クリエーターズライブ2010"
      }
    ]
  },
  {
    "day": "5",
    "events": [
      {
        "desc": [
          "堀田篤(g)先生"
        ],
        "begin": "2010-09-05T15:00:00+09:00",
        "end": "2010-09-05T16:30:00+09:00",
        "title": "はじめてファンク"
      },
      {
        "desc": [],
        "begin": "2010-09-05T16:30:00+09:00",
        "end": "2010-09-05T18:00:00+09:00",
        "title": "超超初心者ファンク"
      },
      {
        "desc": [],
        "begin": "2010-09-05T18:00:00+09:00",
        "end": "2010-09-05T19:30:00+09:00",
        "title": "超初心者ファンク"
      },
      {
        "desc": [
          "堀田篤(g)",
          "吉川遼(ds)",
          "チャージ：2,000円",
          "(フリードリンク付)",
          "☆当日19：30までのレッスン参加者はチャージ1000円でOK!!",
          "☆予約なしでOK！"
        ],
        "begin": "2010-09-05T20:00:00+09:00",
        "end": "2010-09-05T23:00:00+09:00",
        "title": "FUNK JAM"
      }
    ]
  },
  {
    "day": "6",
    "events": [
      {
        "desc": [
          "★9月新規開講★",
          "&lt;&lt;9/6〜12/6&gt;&gt;",
          "課題曲：",
          "Fブルース",
          "講師：中野沙織(p)",
          "◆ 入会金　無料！！",
          "◆ 全12回　15,000円　前払い制",
          "◆ 1レッスン60分、フリードリンク付"
        ],
        "begin": "2010-09-06T19:00:00+09:00",
        "end": "2010-09-06T20:00:00+09:00",
        "title": "ジャズ基本マスター・3カ月コース"
      },
      {
        "desc": [
          "7月開講クラス",
          "&lt;&lt;7/5〜10/25&gt;&gt;"
        ],
        "begin": "2010-09-06T20:15:00+09:00",
        "end": "2010-09-06T21:15:00+09:00",
        "title": "ジャズ基本マスター・3カ月コース"
      }
    ]
  },
  {
    "day": "7",
    "events": [
      {
        "desc": [
          "6月開講",
          "&lt;&lt;6/1〜9/7&gt;&gt;"
        ],
        "begin": "2010-09-07T19:00:00+09:00",
        "end": "2010-09-07T20:00:00+09:00",
        "title": "ジャズ基本マスター・3カ月コース"
      },
      {
        "desc": [
          "7月開講クラス",
          "&lt;&lt;7/6〜10/12&gt;&gt;"
        ],
        "begin": "2010-09-07T20:15:00+09:00",
        "end": "2010-09-07T21:15:00+09:00",
        "title": "ジャズ中級マスター・3カ月コース"
      }
    ]
  },
  {
    "day": "8",
    "events": [
      {
        "desc": [
          "★ダブルフロア行き来自由!!",
          "★ご予約は、",
          "Ｂ1スケジュール",
          "から"
        ],
        "begin": "2010-09-08T21:30:00+09:00",
        "end": "2010-09-08T23:00:00+09:00",
        "title": "超超初心者ジャズ〜初心者ジャズ"
      }
    ]
  },
  {
    "day": "9",
    "events": [
      {
        "desc": [
          "img src=\"http://somethinjazz.com/img/darec.jpg\" border=\"0\"",
          "元チキンシャックのオリジナルメンバーだったベーシスト/ボーカリスト/プロデューサーのDarek Jacksonが、マイルスカフェに初登場！",
          "陀礼久 Darek Jackson(b,vo)",
          "羽仁知治(key)",
          "ハンク西山(gt)",
          "岩原大輔(per)",
          "平陸(ds)",
          "海野あゆみ(sax)",
          "予約:2,500円",
          "当日:3,000円",
          "別途1ドリンク600円"
        ],
        "begin": "2010-09-09T20:00:00+09:00",
        "end": "2010-09-09T23:00:00+09:00",
        "title": "Darek　Jackson　Band　&quot;SPAM&quot;"
      }
    ]
  },
  {
    "day": "10",
    "events": [
      {
        "desc": [
          "img src=\"http://somethinjazz.com/img/jam.jpg\" border=\"0\"",
          "吉田 博(vo)",
          "井上&quot;KB&quot;幸法(g)",
          "北川 淳人(b)",
          "浜野 滋(ds)",
          "Soul/R&amp;B系中心のジャムセッション。ボーカルの方も楽器の方も気軽に遊びに来て下さい！みんなで音出して、音楽を作りましょう！見学も自由です。",
          "ボーカルの方はやりたい曲の譜面などお持ちいただけると進行がスムーズになります。",
          "★予約なしでもOK！",
          "2,000円(1ドリンク付き)"
        ],
        "begin": "2010-09-10T20:00:00+09:00",
        "end": "2010-09-10T23:00:00+09:00",
        "title": "SOUL JAM"
      }
    ]
  },
  {
    "day": "11",
    "events": []
  },
  {
    "day": "12",
    "events": [
      {
        "desc": [
          "堀田篤(g)先生"
        ],
        "begin": "2010-09-12T15:00:00+09:00",
        "end": "2010-09-12T16:30:00+09:00",
        "title": "はじめてファンク"
      },
      {
        "desc": [],
        "begin": "2010-09-12T16:30:00+09:00",
        "end": "2010-09-12T18:00:00+09:00",
        "title": "超超初心者ファンク"
      },
      {
        "desc": [],
        "begin": "2010-09-12T18:00:00+09:00",
        "end": "2010-09-12T19:30:00+09:00",
        "title": "超初心者ファンク"
      },
      {
        "desc": [
          "堀田篤(g)",
          "吉川遼(ds)",
          "チャージ：2,000円",
          "(フリードリンク付)",
          "☆当日19：30までのレッスン参加者はチャージ1000円でOK!!",
          "☆予約なしでOK！"
        ],
        "begin": "2010-09-12T20:00:00+09:00",
        "end": "2010-09-12T23:00:00+09:00",
        "title": "FUNK JAM"
      }
    ]
  },
  {
    "day": "13",
    "events": [
      {
        "desc": [
          "9月開講クラス",
          "&lt;&lt;9/6〜12/6&gt;&gt;"
        ],
        "begin": "2010-09-13T19:00:00+09:00",
        "end": "2010-09-13T20:00:00+09:00",
        "title": "ジャズ基本マスター・3カ月コース"
      },
      {
        "desc": [
          "7月開講クラス",
          "&lt;&lt;7/5〜10/25&gt;&gt;"
        ],
        "begin": "2010-09-13T20:15:00+09:00",
        "end": "2010-09-13T21:15:00+09:00",
        "title": "ジャズ基本マスター・3カ月コース"
      }
    ]
  },
  {
    "day": "14",
    "events": [
      {
        "desc": [
          "★9月新規開講★",
          "&lt;&lt;9/14〜12/14&gt;&gt;",
          "課題曲：",
          "Fブルース",
          "講師：三浦トオル(b)",
          "◆ 入会金　無料！！",
          "◆ 全12回　15,000円　前払い制",
          "◆ 1レッスン60分、フリードリンク付"
        ],
        "begin": "2010-09-14T19:00:00+09:00",
        "end": "2010-09-14T20:00:00+09:00",
        "title": "ジャズ基本マスター・3カ月コース"
      },
      {
        "desc": [
          "7月開講クラス",
          "&lt;&lt;7/6〜10/12&gt;&gt;"
        ],
        "begin": "2010-09-14T20:15:00+09:00",
        "end": "2010-09-14T21:15:00+09:00",
        "title": "ジャズ中級マスター・3カ月コース"
      }
    ]
  },
  {
    "day": "15",
    "events": [
      {
        "desc": [
          "【",
          "img src=\"http://www.milescafe.com/img/pon1.jpg\" border=\"0\"",
          "18:00open/19:00start",
          "ただすけ(p)",
          "小畑ポンプ(ds)",
          "ゲスト：越田太郎丸(gt)",
          "渡部沙智子(vo)",
          "前売:4,000円",
          "当日:4,500円",
          "別途1ドリンク600円",
          "★ご予約・詳細・お問合せは、",
          "「ポンすけ」HP",
          "からお願いします"
        ],
        "begin": "2010-09-15T19:00:00+09:00",
        "end": "2010-09-15T22:00:00+09:00"
      }
    ]
  },
  {
    "day": "16",
    "events": []
  },
  {
    "day": "17",
    "events": [
      {
        "desc": [
          "img src=\"http://somethinjazz.com/img/suzuki.jpg\" border=\"0\"",
          "鈴木直人(g)",
          "山田豪(g)",
          "予約:2,500円",
          "当日:3,000円",
          "別途1ドリンク600円"
        ],
        "begin": "2010-09-17T20:00:00+09:00",
        "end": "2010-09-17T23:00:00+09:00",
        "title": "鈴木直人&amp;山田豪 Guitar Duo"
      }
    ]
  },
  {
    "day": "18",
    "events": [
      {
        "desc": [
          "img src=\"http://somethinjazz.com/img/live.jpg\" border=\"0\"",
          "永井健二郎(b)",
          "阿部篤志(p)",
          "田中菜緒子(key)",
          "北岡吾朗(ds)",
          "open18:30",
          "start19:00",
          "予約:2,500円",
          "当日:3,000円",
          "別途1ドリンク600円"
        ],
        "begin": "2010-09-18T19:00:00+09:00",
        "end": "2010-09-18T22:00:00+09:00",
        "title": "永井健二郎セッション"
      }
    ]
  },
  {
    "day": "19",
    "events": [
      {
        "desc": [
          "※堀田篤先生の都合により、この日のファンクレッスンは終日休講です。ご了承下さい。"
        ],
        "title": "はじめてファンク〜FUNK JAM"
      }
    ]
  },
  {
    "day": "20",
    "events": []
  },
  {
    "day": "21",
    "events": [
      {
        "desc": [
          "9月開講クラス",
          "&lt;&lt;9/14〜12/14&gt;&gt;"
        ],
        "begin": "2010-09-21T19:00:00+09:00",
        "end": "2010-09-21T20:00:00+09:00",
        "title": "ジャズ基本マスター・3カ月コース"
      },
      {
        "desc": [
          "7月開講クラス",
          "&lt;&lt;7/6〜10/12&gt;&gt;"
        ],
        "begin": "2010-09-21T20:15:00+09:00",
        "end": "2010-09-21T21:15:00+09:00",
        "title": "ジャズ中級マスター・3カ月コース"
      }
    ]
  },
  {
    "day": "22",
    "events": [
      {
        "desc": [
          "10名様のみ追加予約受付いたします。"
        ],
        "title": "ただまなライブ&lt;追加予約&gt;"
      },
      {
        "desc": [
          "img src=\"http://somethinjazz.com/img/live.jpg\" border=\"0\"",
          "open 19:00",
          "start 19:30",
          "ただすけ(p)",
          "真部裕(vl)",
          "予約:3,000円",
          "当日:3,500円",
          "別途1ドリンク600円"
        ],
        "begin": "2010-09-22T19:30:00+09:00",
        "end": "2010-09-22T22:30:00+09:00",
        "title": "ただまなライブ"
      }
    ]
  },
  {
    "day": "23",
    "events": [
      {
        "desc": [
          "&quot;Crop-Circle&amp;the Homo-sapiens Formula LIVE&quot;",
          "img src=\"http://somethinjazz.com/img/musumiya.jpg\" border=\"0\"",
          "六角屋雄介(as,EWI)",
          "小松雄大(ts,ss)",
          "佐山こうた(p)",
          "佐野俊介(b)",
          "二本松義史(ds)",
          "サックス、EWI奏者六角屋(ムスミヤ)が、クリエイティブなメンバーと送る２管コンテンポラリー・ジャズナイト！！",
          "加護亜依(vo)groupのサポートやToku(fh)とのブルーノート出演で、勢いに乗る二本松義史(ds)のプレーも必見です！",
          "予約：2,200円",
          "当日：2,500円",
          "別途1ドリンク600円"
        ],
        "begin": "2010-09-23T20:00:00+09:00",
        "end": "2010-09-23T23:00:00+09:00",
        "title": "ユウスケ・ムスミヤジャズグループ"
      }
    ]
  },
  {
    "day": "24",
    "events": [
      {
        "desc": [
          "img src=\"http://somethinjazz.com/img/ruike.jpg\" border=\"0\"",
          "類家心平(tp)",
          "山田貴子(p)",
          "予約:2,600円",
          "当日:3,000円",
          "別途1ドリンク600円"
        ],
        "begin": "2010-09-24T20:00:00+09:00",
        "end": "2010-09-24T23:00:00+09:00",
        "title": "類家心平 × 山田貴子 DUO"
      }
    ]
  },
  {
    "day": "25",
    "events": [
      {
        "desc": [
          "ラテンジャズの名曲と1960〜1990のロック・スタンダード＆オリジナル"
        ],
        "begin": "2010-09-25T15:00:00+09:00",
        "end": "2010-09-25T21:00:00+09:00",
        "title": "貸切 - KTP Presents もうひとつの月（1Q83)"
      }
    ]
  },
  {
    "day": "26",
    "events": [
      {
        "desc": [
          "img src=\"http://somethinjazz.com/img/live.jpg\" border=\"0\"",
          "坂上領(fl)",
          "多久潤一朗(fl)",
          "阿部篤志(p)",
          "『sopro』とは「響き」「音」「一吹き」「一陣の風」「吹奏」といった意味。",
          "三人の個性が響き合う。感動あり、笑いあり、ノンジャンルな世界を繰り広げる唯一無二のユニット！衝撃的な音楽体験になること間違いなし！！",
          "予約：3,000円",
          "当日：3,500円",
          "別途1ドリンク600円"
        ],
        "begin": "2010-09-26T20:00:00+09:00",
        "end": "2010-09-26T23:00:00+09:00",
        "title": "『トレス=ソプロス』コンサート ツアー 2010"
      }
    ]
  },
  {
    "day": "27",
    "events": [
      {
        "desc": [
          "9月開講クラス",
          "&lt;&lt;9/6〜12/6&gt;&gt;"
        ],
        "begin": "2010-09-27T19:00:00+09:00",
        "end": "2010-09-27T20:00:00+09:00",
        "title": "ジャズ基本マスター・3カ月コース"
      },
      {
        "desc": [
          "7月開講クラス",
          "&lt;&lt;7/5〜10/25&gt;&gt;"
        ],
        "begin": "2010-09-27T20:15:00+09:00",
        "end": "2010-09-27T21:15:00+09:00",
        "title": "ジャズ基本マスター・3カ月コース"
      }
    ]
  },
  {
    "day": "28",
    "events": [
      {
        "desc": [
          "9月開講クラス",
          "&lt;&lt;9/14〜12/14&gt;&gt;"
        ],
        "begin": "2010-09-28T19:00:00+09:00",
        "end": "2010-09-28T20:00:00+09:00",
        "title": "ジャズ基本マスター・3カ月コース"
      },
      {
        "desc": [
          "7月開講クラス",
          "&lt;&lt;7/6〜10/12&gt;&gt;"
        ],
        "begin": "2010-09-28T20:15:00+09:00",
        "end": "2010-09-28T21:15:00+09:00",
        "title": "ジャズ中級マスター・3カ月コース"
      }
    ]
  },
  {
    "day": "29",
    "events": [
      {
        "desc": [
          "★ダブルフロア行き来自由!!",
          "★ご予約は、",
          "Ｂ1スケジュール",
          "から"
        ],
        "begin": "2010-09-29T21:30:00+09:00",
        "end": "2010-09-29T23:00:00+09:00",
        "title": "超超初心者ジャズ〜初心者ジャズ"
      }
    ]
  },
  {
    "day": "30",
    "events": [
      {
        "desc": [
          "img src=\"http://somethinjazz.com/img/jam.jpg\" border=\"0\"",
          "吉田博(vo)",
          "井上&quot;KB&quot;幸法(g)",
          "Gakushi(key)",
          "瀧元風喜(b)",
          "瀧元寛太(ds)",
          "open mic形式のjam session！",
          "nu soul,R&amp;B,classic soulが好きなおすすめです。",
          "シンガーの方、歓迎です！ミュージシャンもぜひお越し下さい！",
          "チャージ：2500円",
          "(1ドリンク付き)"
        ],
        "begin": "2010-09-30T20:00:00+09:00",
        "end": "2010-09-30T23:00:00+09:00",
        "title": "nu soul jam"
      }
    ]
  }
]